fastapi_healthcheck/__init__.py
fastapi_healthcheck/domain.py
fastapi_healthcheck/enum.py
fastapi_healthcheck/model.py
fastapi_healthcheck/route.py
fastapi_healthcheck/service.py
fastapi_healthcheck-0.2.13.dist-info/LICENSE
fastapi_healthcheck-0.2.13.dist-info/METADATA
fastapi_healthcheck-0.2.13.dist-info/WHEEL
fastapi_healthcheck-0.2.13.dist-info/RECORD
