Metadata-Version: 2.1
Name: fastapi_healthcheck
Version: 0.2.13
Summary: Base package to handle health checks with FastAPI.
Home-page: https://github.com/jtom38/fastapi_healthcheck
License: MIT
Author: James Tombleson
Author-email: luther38@gmail.com
Requires-Python: >=3.9,<4.0
Classifier: Development Status :: 3 - Alpha
Classifier: Framework :: FastAPI
Classifier: License :: OSI Approved :: MIT License
Classifier: Programming Language :: Python :: 3
Classifier: Programming Language :: Python :: 3.9
Classifier: Programming Language :: Python :: 3.10
Classifier: Programming Language :: Python :: 3.11
Classifier: Programming Language :: Python :: 3.12
Requires-Dist: fastapi (>=0,<1)
Requires-Dist: pydantic (>=2.5.2,<3.0.0)
Project-URL: Repository, https://github.com/jtom38/fastapi_healthcheck
